Workbook

Sheet Plan Pricing
A1: KW GROWTH ENGINE - SUBSCRIPTION PLAN PRICING (KWD)
A3: Feature / Limit | B3: Starter | C3: Growth | D3: Enterprise | E3: Notes
A4: Monthly Price (KWD) | B4: 9.9 | C4: 29.9 | D4: 79.9 | E4: Billed monthly
A5: Yearly Price (KWD) | B5: 99 | C5: 299 | D5: 799 | E5: Billed annually (save ~17%)
A6: Yearly Discount % | B6: =1-(B5/(B4*12)) -> 0 | C6: =1-(C5/(C4*12)) -> 0 | D6: =1-(D5/(D4*12)) -> 0 | E6: Formula
A8: FEATURE LIMITS
A9: Max Contacts | B9: 500 | C9: 5000 | D9: 50000
A10: Conversations / Month | B10: 1000 | C10: 10000 | D10: 100000
A11: Team Members | B11: 3 | C11: 10 | D11: 50
A12: Automations | B12: 5 | C12: 25 | D12: 100
A13: Pipelines | B13: 1 | C13: 3 | D13: 10
A14: Landing Pages | B14: 3 | C14: 10 | D14: 50
A15: AI Dialect Engine | B15: No | C15: Yes | D15: Yes | E15: Claude API powered
A16: API Access | B16: No | C16: No | D16: Yes | E16: REST API + Webhooks
A17: WhatsApp Templates | B17: Yes | C17: Yes | D17: Yes | E17: Included
A18: Shipping Integration | B18: Yes | C18: Yes | D18: Yes | E18: Aramex/DHL/Fetchr
A19: Chatbot Flow Builder | B19: Basic | C19: Full | D19: Full | E19: Visual editor
A20: Campaigns / Broadcasts | B20: 3/mo | C20: Unlimited | D20: Unlimited | E20: Bulk WhatsApp
A21: Data Export (CSV) | B21: No | C21: Yes | D21: Yes | E21: Contacts/Deals/Convos
A22: Custom Reports | B22: No | C22: No | D22: Yes | E22: Report builder
A23: Support Level | B23: Email | C23: Email+Chat | D23: Priority+Phone

Sheet Infrastructure Cost
A1: MONTHLY INFRASTRUCTURE COST PER CUSTOMER (KWD)
A2: Assumptions: AWS me-south-1 (Bahrain) | 1 KWD = 3.26 USD | Shared infra allocated by tier
A4: Cost Component | B4: Starter | C4: Growth | D4: Enterprise | E4: Source / Notes
A5: ASSUMPTIONS
A6: Assumed Customers per Tier | B6: 100 | C6: 30 | D6: 5 | E6: Editable assumption (blue)
A8: AWS INFRASTRUCTURE (shared)
A9: EC2 (2x t3.medium API + 2x worker) | B9: 0.45 | C9: 0.9 | D9: 1.8 | E9: $97/mo total, allocated by tier weight
A10: RDS PostgreSQL 16 (db.t3.medium multi-AZ) | B10: 0.25 | C10: 0.5 | D10: 1 | E10: $163/mo total, 14-day backup
A11: ElastiCache Redis (cache.t3.medium x2) | B11: 0.1 | C11: 0.2 | D11: 0.4 | E11: $65/mo total
A12: S3 Storage (media files) | B12: 0.02 | C12: 0.1 | D12: 0.5 | E12: $0.023/GB stored
A13: ALB + Data Transfer | B13: 0.05 | C13: 0.1 | D13: 0.3 | E13: $25/mo ALB + $0.09/GB out
A14: Total AWS per Customer | B14: =SUM(B9:B13) -> 0 | C14: =SUM(C9:C13) -> 0 | D14: =SUM(D9:D13) -> 0 | E14: Formula: sum of AWS costs
A16: WHATSAPP API (Meta 2026 pricing)
A17: Service Convos (24h free window) | B17: 0 | C17: 0 | D17: 0 | E17: Free: customer-initiated replies
A18: Marketing Messages (~10-20% of convos) | B18: 0.2 | C18: 1.5 | D18: 10 | E18: ~$0.065/msg avg, varies by country
A19: Utility Messages (~5% of convos) | B19: 0.05 | C19: 0.3 | D19: 2 | E19: ~$0.025/msg avg (order updates, tracking)
A20: Total WhatsApp API per Customer | B20: =SUM(B17:B19) -> 0 | C20: =SUM(C17:C19) -> 0 | D20: =SUM(D17:D19) -> 0 | E20: Formula: sum of WA costs
A22: AI ENGINE (Anthropic Claude Haiku)
A23: Claude API calls/month | B23: 0 | C23: 0.15 | D23: 0.8 | E23: Starter: no AI. $0.25/1M input tokens
A25: PAYMENT PROCESSING (Tap)
A26: Tap fee on subscription (2.65%) | B26: ='Plan Pricing'!B4*0.0265 -> 0 | C26: ='Plan Pricing'!C4*0.0265 -> 0 | D26: ='Plan Pricing'!D4*0.0265 -> 0 | E26: K-Net ~1.5%, Visa/MC ~2.65%
A28: OTHER COSTS
A29: Domain + SSL Certificate | B29: 0.005 | C29: 0.005 | D29: 0.005 | E29: $15/yr shared
A30: Sentry Error Tracking | B30: 0.01 | C30: 0.01 | D30: 0.01 | E30: $26/mo team plan shared
A31: Email (AWS SES) | B31: 0.002 | C31: 0.01 | D31: 0.05 | E31: $0.10/1000 emails
A33: TOTAL COST PER CUSTOMER / MONTH | B33: =B14+B20+B23+B26+SUM(B29:B31) -> 0 | C33: =C14+C20+C23+C26+SUM(C29:C31) -> 0 | D33: =D14+D20+D23+D26+SUM(D29:D31) -> 0 | E33: Sum: AWS + WhatsApp + AI + Tap + Other

Sheet Profit Analysis
A1: PROFIT & MARGIN ANALYSIS PER CUSTOMER (KWD/MONTH)
A3: Metric | B3: Starter | C3: Growth | D3: Enterprise | E3: Calculation
A4: Monthly Revenue (Plan Price) | B4: ='Plan Pricing'!B4 -> 0 | C4: ='Plan Pricing'!C4 -> 0 | D4: ='Plan Pricing'!D4 -> 0 | E4: From Plan Pricing sheet
A5: Total Cost per Customer | B5: ='Infrastructure Cost'!B33 -> 0 | C5: ='Infrastructure Cost'!C33 -> 0 | D5: ='Infrastructure Cost'!D33 -> 0 | E5: From Infrastructure Cost sheet
A7: GROSS PROFIT / MONTH | B7: =B4-B5 -> 0 | C7: =C4-C5 -> 0 | D7: =D4-D5 -> 0 | E7: Revenue - Cost
A8: GROSS MARGIN % | B8: =IF(B4>0,B7/B4,0) -> 0 | C8: =IF(C4>0,C7/C4,0) -> 0 | D8: =IF(D4>0,D7/D4,0) -> 0 | E8: Profit / Revenue
A10: ANNUAL METRICS
A11: Annual Revenue (monthly billing) | B11: =B4*12 -> 0
C12: =C4*12 -> 0
D13: =D4*12 -> 0
A14: Annual Revenue (yearly billing) | B14: ='Plan Pricing'!B5 -> 0
C15: ='Plan Pricing'!C5 -> 0
D16: ='Plan Pricing'!D5 -> 0
A17: Annual Cost | B17: =B5*12 -> 0
C18: =C5*12 -> 0
D19: =D5*12 -> 0
A20: Annual Profit (monthly billing) | B20: =B4*12-B19 -> 0
C21: =C4*12-C19 -> 0
D22: =D4*12-D19 -> 0
A23: Annual Profit (yearly billing) | B23: ='Plan Pricing'!B5-B19 -> 0
C25: ='Plan Pricing'!C5-C19 -> 0
D27: ='Plan Pricing'!D5-D19 -> 0
A29: FLEET ECONOMICS (all customers)
A30: Customers per Tier | B30: ='Infrastructure Cost'!B6 -> 0
C31: ='Infrastructure Cost'!C6 -> 0
D32: ='Infrastructure Cost'!D6 -> 0
A33: Monthly Fleet Revenue | B33: =B4*B32 -> 0
C34: =C4*C32 -> 0
D35: =D4*D32 -> 0
A36: Monthly Fleet Cost | B36: =B5*B32 -> 0
C37: =C5*C32 -> 0
D38: =D5*D32 -> 0
A39: MONTHLY FLEET PROFIT | B39: =B35-B38 -> 0
C40: =C35-C38 -> 0
D41: =D35-D38 -> 0
A42: ANNUAL FLEET PROFIT | B42: =B41*12 -> 0
C44: =C41*12 -> 0
D46: =D41*12 -> 0
A48: TOTAL ANNUAL PROFIT (ALL TIERS) | B48: =B41*12+C41*12+D41*12 -> 0 | E48: Combined profit from all tiers

Sheet Competitor Comparison
A1: COMPETITOR PRICING COMPARISON (Monthly)
A3: Plan Tier | B3: KW Growth (KWD) | C3: KW Growth (USD) | D3: Respond.io (USD) | E3: WATI (USD) | F3: SleekFlow (USD)
A4: Entry / Starter | B4: 9.9 | C4: =B4*3.26 -> 0 | D4: 99 | E4: 49 | F4: 79
A5: Mid / Growth | B5: 29.9 | C5: =B5*3.26 -> 0 | D5: 299 | E5: 99 | F5: 299
A6: High / Enterprise | B6: 79.9 | C6: =B6*3.26 -> 0 | D6: 699 | E6: Custom | F6: 599
A8: PRICE ADVANTAGE
A9: vs Respond.io Starter | B9: =C4-D4 -> 0 | C9: savings
A10: vs Respond.io Growth | B10: =C5-D5 -> 0 | C10: savings
A11: vs Respond.io Enterprise | B11: =C6-D6 -> 0 | C11: savings
A13: UNIQUE FEATURES (included)
A14: Kuwait K-Net Payments | B14: Yes | C14: Yes | D14: No | E14: No | F14: No
A15: Kuwaiti Dialect AI | B15: Yes | C15: Yes | D15: No | E15: No | F15: No
A16: Shipping + WhatsApp Tracking | B16: Yes | C16: Yes | D16: No | E16: No | F16: No
A17: Landing Page Builder | B17: Yes | C17: Yes | D17: No | E17: No | F17: No
A18: GCC Data Residency (Bahrain) | B18: Yes | C18: Yes | D18: Partial | E18: No | F18: No
A19: Sales Pipeline / Kanban | B19: Yes | C19: Yes | D19: Yes | E19: No | F19: Yes
A20: Instagram + Facebook DM | B20: Yes | C20: Yes | D20: Yes | E20: Yes | F20: Yes
A21: Visual Chatbot Builder | B21: Yes | C21: Yes | D21: Yes | E21: Yes | F21: Yes
A22: Broadcast Campaigns | B22: Yes | C22: Yes | D22: Yes | E22: Yes | F22: Yes
